LICENSE.txt
MANIFEST.in
README.rst
requirements.txt
setup.py
omego/RELEASE-VERSION
omego/__init__.py
omego/artifacts.py
omego/convert.py
omego/db.py
omego/env.py
omego/external.py
omego/fileutils.py
omego/main.py
omego/upgrade.py
omego/version.py
omego.egg-info/PKG-INFO
omego.egg-info/SOURCES.txt
omego.egg-info/dependency_links.txt
omego.egg-info/entry_points.txt
omego.egg-info/requires.txt
omego.egg-info/top_level.txt
omego.egg-info/zip-safe